setup.py
mffcc_extract_python/__init__.py
mffcc_extract_python/mymath.py
mffcc_extract_python.egg-info/PKG-INFO
mffcc_extract_python.egg-info/SOURCES.txt
mffcc_extract_python.egg-info/dependency_links.txt
mffcc_extract_python.egg-info/not-zip-safe
mffcc_extract_python.egg-info/requires.txt
mffcc_extract_python.egg-info/top_level.txt