Metadata-Version: 1.0
Name: mffcc-extract-python
Version: 1.0
Summary: This is a test for setuptools
Home-page: UNKNOWN
Author: jren
Author-email: jren@massey.ac.nz
License: MIT
Platform: UNKNOWN
